setup.py
Nst1/__init__.py
Nst1/admin.py
Nst1/apps.py
Nst1/fields.py
Nst1/forms.py
Nst1/models.py
Nst1/states.py
Nst1/tests.py
Nst1/views.py
Nst1/migrations/__init__.py
nikhil_indian_states_25/__init__.py
nikhil_indian_states_25/asgi.py
nikhil_indian_states_25/settings.py
nikhil_indian_states_25/urls.py
nikhil_indian_states_25/wsgi.py
nikhil_indian_states_25.egg-info/PKG-INFO
nikhil_indian_states_25.egg-info/SOURCES.txt
nikhil_indian_states_25.egg-info/dependency_links.txt
nikhil_indian_states_25.egg-info/requires.txt
nikhil_indian_states_25.egg-info/top_level.txt